<annotation>
	<folder>Data</folder>
	<filename>2891.jpg</filename>
	<path>/home/datascience/RS/PlumsVOC/JPEGImages/2891.jpg</path>
	<source>
		<database>Unspecified</database>
	</source>
	<size>
		<width>1920</width>
		<height>1080</height>
		<depth>3</depth>
	</size>
	<object>
		<name>Egg</name>
		<pose>Unspecified</pose>
		<truncated>0</truncated>
		<difficult>0</difficult>
		<bndbox>
			<xmin>1795</xmin>
			<ymin>485</ymin>
			<xmax>1826</xmax>
			<ymax>521</ymax>
		</bndbox>
	</object>
	<object>
		<name>Egg</name>
		<pose>Unspecified</pose>
		<truncated>0</truncated>
		<difficult>0</difficult>
		<bndbox>
			<xmin>1680</xmin>
			<ymin>563</ymin>
			<xmax>1714</xmax>
			<ymax>591</ymax>
		</bndbox>
	</object>
	<object>
		<name>Egg</name>
		<pose>Unspecified</pose>
		<truncated>0</truncated>
		<difficult>0</difficult>
		<bndbox>
			<xmin>1747</xmin>
			<ymin>735</ymin>
			<xmax>1783</xmax>
			<ymax>768</ymax>
		</bndbox>
	</object>
</annotation>