<annotation>
	<folder>Data</folder>
	<filename>2941.jpg</filename>
	<path>/home/datascience/RS/PlumsVOC/JPEGImages/2941.jpg</path>
	<source>
		<database>Unspecified</database>
	</source>
	<size>
		<width>1920</width>
		<height>1080</height>
		<depth>3</depth>
	</size>
	<object>
		<name>Egg</name>
		<pose>Unspecified</pose>
		<truncated>0</truncated>
		<difficult>0</difficult>
		<bndbox>
			<xmin>1742</xmin>
			<ymin>736</ymin>
			<xmax>1781</xmax>
			<ymax>760</ymax>
		</bndbox>
	</object>
	<object>
		<name>Egg</name>
		<pose>Unspecified</pose>
		<truncated>0</truncated>
		<difficult>0</difficult>
		<bndbox>
			<xmin>1798</xmin>
			<ymin>482</ymin>
			<xmax>1820</xmax>
			<ymax>517</ymax>
		</bndbox>
	</object>
	<object>
		<name>Egg</name>
		<pose>Unspecified</pose>
		<truncated>0</truncated>
		<difficult>0</difficult>
		<bndbox>
			<xmin>1819</xmin>
			<ymin>951</ymin>
			<xmax>1847</xmax>
			<ymax>983</ymax>
		</bndbox>
	</object>
</annotation>